contractpy
